test2_powerhouse_helper-1.data/data/test_powerhouse_helper/AddressBook/address_saves/address_book.log
test2_powerhouse_helper-1.data/data/test_powerhouse_helper/AddressBook/address_saves/address_book_auto_save.bin
test2_powerhouse_helper-1.data/data/test_powerhouse_helper/GameGooseKiller/font/UA Propisi.ttf
test2_powerhouse_helper-1.data/data/test_powerhouse_helper/GameGooseKiller/image/Farm-Goose.ico
test2_powerhouse_helper-1.data/data/test_powerhouse_helper/GameGooseKiller/image/background.png
test2_powerhouse_helper-1.data/data/test_powerhouse_helper/GameGooseKiller/image/bonus.png
test2_powerhouse_helper-1.data/data/test_powerhouse_helper/GameGooseKiller/image/boom.png
test2_powerhouse_helper-1.data/data/test_powerhouse_helper/GameGooseKiller/image/enemy.png
test2_powerhouse_helper-1.data/data/test_powerhouse_helper/GameGooseKiller/image/gameover.png
test2_powerhouse_helper-1.data/data/test_powerhouse_helper/GameGooseKiller/image/Goose/1-1.png
test2_powerhouse_helper-1.data/data/test_powerhouse_helper/GameGooseKiller/image/Goose/1-2.png
test2_powerhouse_helper-1.data/data/test_powerhouse_helper/GameGooseKiller/image/Goose/1-3.png
test2_powerhouse_helper-1.data/data/test_powerhouse_helper/GameGooseKiller/image/Goose/1-4.png
test2_powerhouse_helper-1.data/data/test_powerhouse_helper/GameGooseKiller/image/Goose/1-5.png
test2_powerhouse_helper-1.data/data/test_powerhouse_helper/GameGooseKiller/image/background/1-1.png
test2_powerhouse_helper-1.data/data/test_powerhouse_helper/GameGooseKiller/image/background/1-2.png
test2_powerhouse_helper-1.data/data/test_powerhouse_helper/GameGooseKiller/image/background/1-3.png
test2_powerhouse_helper-1.data/data/test_powerhouse_helper/NoteBook/note_saves/note_book.log
test2_powerhouse_helper-1.data/data/test_powerhouse_helper/NoteBook/note_saves/note_book_auto_save.bin
test_powerhouse_helper/__init__.py
test_powerhouse_helper/main.py
test_powerhouse_helper/AddressBook/Address_Book_Handler.py
test2_powerhouse_helper-1.dist-info/LICENSE
test2_powerhouse_helper-1.dist-info/METADATA
test2_powerhouse_helper-1.dist-info/WHEEL
test2_powerhouse_helper-1.dist-info/entry_points.txt
test2_powerhouse_helper-1.dist-info/top_level.txt
test2_powerhouse_helper-1.dist-info/RECORD
